{"cameraMode":{"drawMode":0,"name":"Shaded","section":"Shading Mode"},"sceneLighting":true,"audioPlay":false,"sceneViewState":{"showFog":true,"showMaterialUpdate":false,"showSkybox":true,"showFlares":true,"showImageEffects":true,"showParticleSystems":true},"in2DMode":false,"pivot":{"x":212.46484375,"y":-79.97586059570313,"z":-1644.1494140625},"rotation":{"x":-0.04262957721948624,"y":-0.9573728442192078,"z":0.19808343052864076,"w":-0.20657576620578767},"size":247.71334838867188,"orthographic":false}